#[derive(Copy, Clone, Debug, PartialEq)]
pub enum jvm_instruction_t {
    i_nop = 0x0,
    i_iconst_m1 = 0x2,
    i_iconst_0 = 0x3,
    i_iconst_1 = 0x4,
    i_iconst_2 = 0x5,
    i_iconst_3 = 0x6,
    i_iconst_4 = 0x7,
    i_iconst_5 = 0x8,
    i_bipush = 0x10,
    i_sipush = 0x11,
    i_ldc = 0x12,
    i_iload = 0x15,
    i_aload = 0x19,
    i_iload_0 = 0x1a,
    i_iload_1 = 0x1b,
    i_iload_2 = 0x1c,
    i_iload_3 = 0x1d,
    i_aload_0 = 0x2a,
    i_aload_1 = 0x2b,
    i_aload_2 = 0x2c,
    i_aload_3 = 0x2d,
    i_iaload = 0x2e,
    i_istore = 0x36,
    i_astore = 0x3a,
    i_istore_0 = 0x3b,
    i_istore_1 = 0x3c,
    i_istore_2 = 0x3d,
    i_istore_3 = 0x3e,
    i_astore_0 = 0x4b,
    i_astore_1 = 0x4c,
    i_astore_2 = 0x4d,
    i_astore_3 = 0x4e,
    i_iastore = 0x4f,
    i_dup = 0x59,
    i_iadd = 0x60,
    i_isub = 0x64,
    i_imul = 0x68,
    i_idiv = 0x6c,
    i_irem = 0x70,
    i_ineg = 0x74,
    i_ishl = 0x78,
    i_ishr = 0x7a,
    i_iushr = 0x7c,
    i_iand = 0x7e,
    i_ior = 0x80,
    i_ixor = 0x82,
    i_iinc = 0x84,
    i_ifeq = 0x99,
    i_ifne = 0x9a,
    i_iflt = 0x9b,
    i_ifge = 0x9c,
    i_ifgt = 0x9d,
    i_ifle = 0x9e,
    i_if_icmpeq = 0x9f,
    i_if_icmpne = 0xa0,
    i_if_icmplt = 0xa1,
    i_if_icmpge = 0xa2,
    i_if_icmpgt = 0xa3,
    i_if_icmple = 0xa4,
    i_goto = 0xa7,
    i_ireturn = 0xac,
    i_areturn = 0xb0,
    i_return = 0xb1,
    i_getstatic = 0xb2,
    i_invokevirtual = 0xb6,
    i_invokestatic = 0xb8,
    i_newarray = 0xbc,
    i_arraylength = 0xbe,
}

impl std::convert::TryFrom<u8> for jvm_instruction_t {
    type Error = ();

    fn try_from(v: u8) -> Result<Self, Self::Error> {
        match v {
            0x0 => Ok(jvm_instruction_t::i_nop),
            0x2 => Ok(jvm_instruction_t::i_iconst_m1),
            0x3 => Ok(jvm_instruction_t::i_iconst_0),
            0x4 => Ok(jvm_instruction_t::i_iconst_1),
            0x5 => Ok(jvm_instruction_t::i_iconst_2),
            0x6 => Ok(jvm_instruction_t::i_iconst_3),
            0x7 => Ok(jvm_instruction_t::i_iconst_4),
            0x8 => Ok(jvm_instruction_t::i_iconst_5),
            0x10 => Ok(jvm_instruction_t::i_bipush),
            0x11 => Ok(jvm_instruction_t::i_sipush),
            0x12 => Ok(jvm_instruction_t::i_ldc),
            0x15 => Ok(jvm_instruction_t::i_iload),
            0x19 => Ok(jvm_instruction_t::i_aload),
            0x1a => Ok(jvm_instruction_t::i_iload_0),
            0x1b => Ok(jvm_instruction_t::i_iload_1),
            0x1c => Ok(jvm_instruction_t::i_iload_2),
            0x1d => Ok(jvm_instruction_t::i_iload_3),
            0x2a => Ok(jvm_instruction_t::i_aload_0),
            0x2b => Ok(jvm_instruction_t::i_aload_1),
            0x2c => Ok(jvm_instruction_t::i_aload_2),
            0x2d => Ok(jvm_instruction_t::i_aload_3),
            0x2e => Ok(jvm_instruction_t::i_iaload),
            0x36 => Ok(jvm_instruction_t::i_istore),
            0x3a => Ok(jvm_instruction_t::i_astore),
            0x3b => Ok(jvm_instruction_t::i_istore_0),
            0x3c => Ok(jvm_instruction_t::i_istore_1),
            0x3d => Ok(jvm_instruction_t::i_istore_2),
            0x3e => Ok(jvm_instruction_t::i_istore_3),
            0x4b => Ok(jvm_instruction_t::i_astore_0),
            0x4c => Ok(jvm_instruction_t::i_astore_1),
            0x4d => Ok(jvm_instruction_t::i_astore_2),
            0x4e => Ok(jvm_instruction_t::i_astore_3),
            0x4f => Ok(jvm_instruction_t::i_iastore),
            0x59 => Ok(jvm_instruction_t::i_dup),
            0x60 => Ok(jvm_instruction_t::i_iadd),
            0x64 => Ok(jvm_instruction_t::i_isub),
            0x68 => Ok(jvm_instruction_t::i_imul),
            0x6c => Ok(jvm_instruction_t::i_idiv),
            0x70 => Ok(jvm_instruction_t::i_irem),
            0x74 => Ok(jvm_instruction_t::i_ineg),
            0x78 => Ok(jvm_instruction_t::i_ishl),
            0x7a => Ok(jvm_instruction_t::i_ishr),
            0x7c => Ok(jvm_instruction_t::i_iushr),
            0x7e => Ok(jvm_instruction_t::i_iand),
            0x80 => Ok(jvm_instruction_t::i_ior),
            0x82 => Ok(jvm_instruction_t::i_ixor),
            0x84 => Ok(jvm_instruction_t::i_iinc),
            0x99 => Ok(jvm_instruction_t::i_ifeq),
            0x9a => Ok(jvm_instruction_t::i_ifne),
            0x9b => Ok(jvm_instruction_t::i_iflt),
            0x9c => Ok(jvm_instruction_t::i_ifge),
            0x9d => Ok(jvm_instruction_t::i_ifgt),
            0x9e => Ok(jvm_instruction_t::i_ifle),
            0x9f => Ok(jvm_instruction_t::i_if_icmpeq),
            0xa0 => Ok(jvm_instruction_t::i_if_icmpne),
            0xa1 => Ok(jvm_instruction_t::i_if_icmplt),
            0xa2 => Ok(jvm_instruction_t::i_if_icmpge),
            0xa3 => Ok(jvm_instruction_t::i_if_icmpgt),
            0xa4 => Ok(jvm_instruction_t::i_if_icmple),
            0xa7 => Ok(jvm_instruction_t::i_goto),
            0xac => Ok(jvm_instruction_t::i_ireturn),
            0xb0 => Ok(jvm_instruction_t::i_areturn),
            0xb1 => Ok(jvm_instruction_t::i_return),
            0xb2 => Ok(jvm_instruction_t::i_getstatic),
            0xb6 => Ok(jvm_instruction_t::i_invokevirtual),
            0xb8 => Ok(jvm_instruction_t::i_invokestatic),
            0xbc => Ok(jvm_instruction_t::i_newarray),
            0xbe => Ok(jvm_instruction_t::i_arraylength),
            _ => Err(()),
        }
    }
}

impl std::convert::TryFrom<i32> for jvm_instruction_t {
    type Error = ();

    fn try_from(v: i32) -> Result<Self, Self::Error> {
        match v {
            0x0 => Ok(jvm_instruction_t::i_nop),
            0x2 => Ok(jvm_instruction_t::i_iconst_m1),
            0x3 => Ok(jvm_instruction_t::i_iconst_0),
            0x4 => Ok(jvm_instruction_t::i_iconst_1),
            0x5 => Ok(jvm_instruction_t::i_iconst_2),
            0x6 => Ok(jvm_instruction_t::i_iconst_3),
            0x7 => Ok(jvm_instruction_t::i_iconst_4),
            0x8 => Ok(jvm_instruction_t::i_iconst_5),
            0x10 => Ok(jvm_instruction_t::i_bipush),
            0x11 => Ok(jvm_instruction_t::i_sipush),
            0x12 => Ok(jvm_instruction_t::i_ldc),
            0x15 => Ok(jvm_instruction_t::i_iload),
            0x19 => Ok(jvm_instruction_t::i_aload),
            0x1a => Ok(jvm_instruction_t::i_iload_0),
            0x1b => Ok(jvm_instruction_t::i_iload_1),
            0x1c => Ok(jvm_instruction_t::i_iload_2),
            0x1d => Ok(jvm_instruction_t::i_iload_3),
            0x2a => Ok(jvm_instruction_t::i_aload_0),
            0x2b => Ok(jvm_instruction_t::i_aload_1),
            0x2c => Ok(jvm_instruction_t::i_aload_2),
            0x2d => Ok(jvm_instruction_t::i_aload_3),
            0x2e => Ok(jvm_instruction_t::i_iaload),
            0x36 => Ok(jvm_instruction_t::i_istore),
            0x3a => Ok(jvm_instruction_t::i_astore),
            0x3b => Ok(jvm_instruction_t::i_istore_0),
            0x3c => Ok(jvm_instruction_t::i_istore_1),
            0x3d => Ok(jvm_instruction_t::i_istore_2),
            0x3e => Ok(jvm_instruction_t::i_istore_3),
            0x4b => Ok(jvm_instruction_t::i_astore_0),
            0x4c => Ok(jvm_instruction_t::i_astore_1),
            0x4d => Ok(jvm_instruction_t::i_astore_2),
            0x4e => Ok(jvm_instruction_t::i_astore_3),
            0x4f => Ok(jvm_instruction_t::i_iastore),
            0x59 => Ok(jvm_instruction_t::i_dup),
            0x60 => Ok(jvm_instruction_t::i_iadd),
            0x64 => Ok(jvm_instruction_t::i_isub),
            0x68 => Ok(jvm_instruction_t::i_imul),
            0x6c => Ok(jvm_instruction_t::i_idiv),
            0x70 => Ok(jvm_instruction_t::i_irem),
            0x74 => Ok(jvm_instruction_t::i_ineg),
            0x78 => Ok(jvm_instruction_t::i_ishl),
            0x7a => Ok(jvm_instruction_t::i_ishr),
            0x7c => Ok(jvm_instruction_t::i_iushr),
            0x7e => Ok(jvm_instruction_t::i_iand),
            0x80 => Ok(jvm_instruction_t::i_ior),
            0x82 => Ok(jvm_instruction_t::i_ixor),
            0x84 => Ok(jvm_instruction_t::i_iinc),
            0x99 => Ok(jvm_instruction_t::i_ifeq),
            0x9a => Ok(jvm_instruction_t::i_ifne),
            0x9b => Ok(jvm_instruction_t::i_iflt),
            0x9c => Ok(jvm_instruction_t::i_ifge),
            0x9d => Ok(jvm_instruction_t::i_ifgt),
            0x9e => Ok(jvm_instruction_t::i_ifle),
            0x9f => Ok(jvm_instruction_t::i_if_icmpeq),
            0xa0 => Ok(jvm_instruction_t::i_if_icmpne),
            0xa1 => Ok(jvm_instruction_t::i_if_icmplt),
            0xa2 => Ok(jvm_instruction_t::i_if_icmpge),
            0xa3 => Ok(jvm_instruction_t::i_if_icmpgt),
            0xa4 => Ok(jvm_instruction_t::i_if_icmple),
            0xa7 => Ok(jvm_instruction_t::i_goto),
            0xac => Ok(jvm_instruction_t::i_ireturn),
            0xb0 => Ok(jvm_instruction_t::i_areturn),
            0xb1 => Ok(jvm_instruction_t::i_return),
            0xb2 => Ok(jvm_instruction_t::i_getstatic),
            0xb6 => Ok(jvm_instruction_t::i_invokevirtual),
            0xb8 => Ok(jvm_instruction_t::i_invokestatic),
            0xbc => Ok(jvm_instruction_t::i_newarray),
            0xbe => Ok(jvm_instruction_t::i_arraylength),
            _ => Err(()),
        }
    }
}
